[{"p": "380059", "s": "GUJARAT", "c": "Ahmedabad"},
  {"p": "392180", "s": "GUJARAT", "c": "Bharuch"},
  {"p": "382740", "s": "GUJARAT", "c": "Gandhi Nagar"},
  {"p": "396126", "s": "GUJARAT", "c": "Valsad"},
  {"p": "394375", "s": "GUJARAT", "c": "Surat"}, {"p": "364320", "s": "GUJARAT", "c": "Bhavnagar"},
  {"p": "396191", "s": "GUJARAT", "c": "Valsad"}, {"p": "388270", "s": "GUJARAT", "c": "Panch Mahals"},
  {"p": "394326", "s": "GUJARAT", "c": "Surat"}, {"p": "394150", "s": "GUJARAT", "c": "Surat"},
  {"p": "364330", "s": "GUJARAT", "c": "Bhavnagar"}, {"p": "360575", "s": "GUJARAT", "c": "Porbandar"},
  {"p": "364081", "s": "GUJARAT", "c": "Bhavnagar"}, {"p": "384210", "s": "GUJARAT", "c": "Mahesana"},
  {"p": "364313", "s": "GUJARAT", "c": "Bhavnagar"}, {"p": "370511", "s": "GUJARAT", "c": "Kachchh"},
  {"p": "396035", "s": "GUJARAT", "c": "Valsad"}, {"p": "361230", "s": "GUJARAT", "c": "Jamnagar"},
  {"p": "392215", "s": "GUJARAT", "c": "Bharuch"}, {"p": "382460", "s": "GUJARAT", "c": "Ahmedabad"},
  {"p": "370165", "s": "GUJARAT", "c": "Kachchh"}, {"p": "383305", "s": "GUJARAT", "c": "Sabarkantha"},
  {"p": "361009", "s": "GUJARAT", "c": "Jamnagar"}, {"p": "384001", "s": "GUJARAT", "c": "Mahesana"},
  {"p": "390009", "s": "GUJARAT", "c": "Vadodara"}, {"p": "361162", "s": "GUJARAT", "c": "Jamnagar"},
  {"p": "364002", "s": "GUJARAT", "c": "Bhavnagar"}, {"p": "380055", "s": "GUJARAT", "c": "Ahmedabad"},
  {"p": "364250", "s": "GUJARAT", "c": "Bhavnagar"}, {"p": "388625", "s": "GUJARAT", "c": "Anand"},
  {"p": "388510", "s": "GUJARAT", "c": "Anand"}, {"p": "370135", "s": "GUJARAT", "c": "Kachchh"},
  {"p": "389390", "s": "GUJARAT", "c": "Panch Mahals"}, {"p": "385410", "s": "GUJARAT", "c": "Banaskantha"},
  {"p": "394340", "s": "GUJARAT", "c": "Surat"}, {"p": "388440", "s": "GUJARAT", "c": "Kheda"},
  {"p": "387340", "s": "GUJARAT", "c": "Kheda"}, {"p": "363410", "s": "GUJARAT", "c": "Surendra Nagar"},
  {"p": "392025", "s": "GUJARAT", "c": "Bharuch"}, {"p": "364001", "s": "GUJARAT", "c": "Bhavnagar"},
  {"p": "391780", "s": "GUJARAT", "c": "Vadodara"}, {"p": "392015", "s": "GUJARAT", "c": "Bharuch"},
  {"p": "385130", "s": "GUJARAT", "c": "Banaskantha"}, {"p": "388710", "s": "GUJARAT", "c": "Vadodara"},
  {"p": "364530", "s": "GUJARAT", "c": "Amreli"}, {"p": "361001", "s": "GUJARAT", "c": "Jamnagar"},
  {"p": "389175", "s": "GUJARAT", "c": "Dahod"}, {"p": "360590", "s": "GUJARAT", "c": "Jamnagar"},
  {"p": "382725", "s": "GUJARAT", "c": "Gandhi Nagar"}, {"p": "360375", "s": "GUJARAT", "c": "Rajkot"},
  {"p": "396115", "s": "GUJARAT", "c": "Valsad"}, {"p": "362725", "s": "GUJARAT", "c": "Junagadh"},
  {"p": "364310", "s": "GUJARAT", "c": "Bhavnagar"}, {"p": "388310", "s": "GUJARAT", "c": "Anand"},
  {"p": "362620", "s": "GUJARAT", "c": "Junagadh"}, {"p": "383270", "s": "GUJARAT", "c": "Sabarkantha"},
  {"p": "370620", "s": "GUJARAT", "c": "Kachchh"}, {"p": "391421", "s": "GUJARAT", "c": "Vadodara"},
  {"p": "382130", "s": "GUJARAT", "c": "Surendra Nagar"}, {"p": "393151", "s": "GUJARAT", "c": "Narmada"},
  {"p": "385565", "s": "GUJARAT", "c": "Banaskantha"}, {"p": "392210", "s": "GUJARAT", "c": "Bharuch"},
  {"p": "395023", "s": "GUJARAT", "c": "Surat"}, {"p": "382750", "s": "GUJARAT", "c": "Surendra Nagar"},
  {"p": "396385", "s": "GUJARAT", "c": "Valsad"}, {"p": "364515", "s": "GUJARAT", "c": "Amreli"},
  {"p": "360070", "s": "GUJARAT", "c": "Rajkot"}, {"p": "362226", "s": "GUJARAT", "c": "Junagadh"},
  {"p": "383205", "s": "GUJARAT", "c": "Sabarkantha"}, {"p": "383345", "s": "GUJARAT", "c": "Sabarkantha"},
  {"p": "363520", "s": "GUJARAT", "c": "Surendra Nagar"}, {"p": "382255", "s": "GUJARAT", "c": "Ahmedabad"},
  {"p": "388465", "s": "GUJARAT", "c": "Anand"}, {"p": "388180", "s": "GUJARAT", "c": "Anand"},
  {"p": "383434", "s": "GUJARAT", "c": "Sabarkantha"}, {"p": "393020", "s": "GUJARAT", "c": "Bharuch"},
  {"p": "385001", "s": "GUJARAT", "c": "Banaskantha"}, {"p": "394715", "s": "GUJARAT", "c": "The Dangs"},
  {"p": "365480", "s": "GUJARAT", "c": "Rajkot"}, {"p": "394155", "s": "GUJARAT", "c": "Surat"},
  {"p": "382745", "s": "GUJARAT", "c": "Surendra Nagar"}, {"p": "382021", "s": "GUJARAT", "c": "Gandhi Nagar"},
  {"p": "362650", "s": "GUJARAT", "c": "Porbandar"}, {"p": "393120", "s": "GUJARAT", "c": "Bharuch"},
  {"p": "383340", "s": "GUJARAT", "c": "Sabarkantha"}, {"p": "383330", "s": "GUJARAT", "c": "Sabarkantha"},
  {"p": "382424", "s": "GUJARAT", "c": "Gandhi Nagar"}, {"p": "364505", "s": "GUJARAT", "c": "Bhavnagar"},
  {"p": "382423", "s": "GUJARAT", "c": "Gandhi Nagar"}, {"p": "360330", "s": "GUJARAT", "c": "Rajkot"},
  {"p": "382715", "s": "GUJARAT", "c": "Mahesana"}, {"p": "392140", "s": "GUJARAT", "c": "Bharuch"},
  {"p": "394110", "s": "GUJARAT", "c": "Surat"}, {"p": "360460", "s": "GUJARAT", "c": "Rajkot"},
  {"p": "388260", "s": "GUJARAT", "c": "Kheda"}, {"p": "391774", "s": "GUJARAT", "c": "Vadodara"},
  {"p": "393020", "s": "GUJARAT", "c": "Narmada"}, {"p": "387230", "s": "GUJARAT", "c": "Kheda"},
  {"p": "363642", "s": "GUJARAT", "c": "Rajkot"}, {"p": "360410", "s": "GUJARAT", "c": "Rajkot"},
  {"p": "392030", "s": "GUJARAT", "c": "Bharuch"}, {"p": "385360", "s": "GUJARAT", "c": "Patan"},
  {"p": "396530", "s": "GUJARAT", "c": "Navsari"}, {"p": "382115", "s": "GUJARAT", "c": "Ahmedabad"},
  {"p": "365635", "s": "GUJARAT", "c": "Amreli"}, {"p": "390008", "s": "GUJARAT", "c": "Vadodara"},
  {"p": "388255", "s": "GUJARAT", "c": "Kheda"}, {"p": "360577", "s": "GUJARAT", "c": "Porbandar"},
  {"p": "380051", "s": "GUJARAT", "c": "Ahmedabad"}, {"p": "394601", "s": "GUJARAT", "c": "Surat"},
  {"p": "360035", "s": "GUJARAT", "c": "Rajkot"}, {"p": "370130", "s": "GUJARAT", "c": "Kachchh"},
  {"p": "394421", "s": "GUJARAT", "c": "Surat"},
  {"p": "360550", "s": "GUJARAT", "c": "Porbandar"}, {"p": "362715", "s": "GUJARAT", "c": "Junagadh"},

  {"p": "363115", "s": "GUJARAT", "c": "Surendra Nagar"}]